polarity/Polarity.py
polarity/__init__.py
polarity/__main__.py
polarity/config.py
polarity/update.py
polarity/utils.py
polarity/version.py
polarity/downloader/__init__.py
polarity/downloader/base.py
polarity/downloader/penguin.py
polarity/downloader/protocols/__init__.py
polarity/downloader/protocols/base.py
polarity/downloader/protocols/dash.py
polarity/downloader/protocols/file.py
polarity/downloader/protocols/hls.py
polarity/extractor/__init__.py
polarity/extractor/atresplayer.py
polarity/extractor/base.py
polarity/extractor/crunchyroll.py
polarity/extractor/flags.py
polarity/extractor/limelight.py
polarity/extractor/pokemontv.py
polarity/lang/__init__.py
polarity/lang/enUS.toml
polarity/lang/esES.toml
polarity/lang/internal.toml
polarity/types/__init__.py
polarity/types/base.py
polarity/types/content.py
polarity/types/download_log.py
polarity/types/ffmpeg.py
polarity/types/filter.py
polarity/types/people.py
polarity/types/progressbar.py
polarity/types/search.py
polarity/types/stream.py
polarity/types/thread.py
Polarity-2022.4.16.post1.dist-info/COPYING
Polarity-2022.4.16.post1.dist-info/METADATA
Polarity-2022.4.16.post1.dist-info/WHEEL
Polarity-2022.4.16.post1.dist-info/entry_points.txt
Polarity-2022.4.16.post1.dist-info/top_level.txt
Polarity-2022.4.16.post1.dist-info/RECORD
