Metadata-Version: 2.1
Name: Polarity
Version: 2022.4.16.post1
Summary: Mass downloader for streaming platforms
Home-page: UNKNOWN
Author: Avery García (aveeryy)
Author-email: aveeryy@protonmail.com
License: GPL-3.0
Platform: unix
Platform: linux
Platform: osx
Platform: cygwin
Platform: win32
Platform: android
Classifier: Programming Language :: Python :: 3
Classifier: Programming Language :: Python :: 3 :: Only
Classifier: Programming Language :: Python :: 3.7
Classifier: Programming Language :: Python :: 3.8
Classifier: Programming Language :: Python :: 3.9
Classifier: Programming Language :: Python :: 3.10
Requires-Python: >=3.7
License-File: COPYING
Requires-Dist: cloudscraper (>=1.2.60)
Requires-Dist: requests (>=2.25.1)
Requires-Dist: m3u8 (>=0.9.0)
Requires-Dist: shtab (>=1.5.3)
Requires-Dist: tomli (>=1.2.3)
Requires-Dist: tomli-W (>=1.0.0)
Requires-Dist: tqdm (>=4.61.1)
Requires-Dist: xmltodict (>=0.12.0)
